analysis3054/__init__.py
analysis3054/aar_rail_traffic.py
analysis3054/advanced.py
analysis3054/api_fetcher.py
analysis3054/auto_ml_forecasting.py
analysis3054/cftc_disagg_dashboard.py
analysis3054/dfo_generators.py
analysis3054/diesel_indicators.py
analysis3054/eia_distillate.py
analysis3054/eia_electricity.py
analysis3054/eia_series.py
analysis3054/eia_wpsr.py
analysis3054/emailer.py
analysis3054/ensembles.py
analysis3054/estimators.py
analysis3054/europe_energy.py
analysis3054/finance.py
analysis3054/forecast_engine.py
analysis3054/forecasting.py
analysis3054/fred_diesel.py
analysis3054/holiday_calendars.py
analysis3054/holiday_lookup.py
analysis3054/inbox_cleaner.py
analysis3054/kayross.py
analysis3054/la_refinery.py
analysis3054/macro_dashboard.py
analysis3054/ml.py
analysis3054/physics_forecaster.py
analysis3054/plot.py
analysis3054/plotly_assets.py
analysis3054/port_houston.py
analysis3054/port_la.py
analysis3054/port_long_beach.py
analysis3054/port_ny.py
analysis3054/port_savannah.py
analysis3054/predict.py
analysis3054/refined_fuels_api.py
analysis3054/refinery_forecast.py
analysis3054/refinery_name_maps.py
analysis3054/regression.py
analysis3054/spain_content.py
analysis3054/statistics.py
analysis3054/stats.py
analysis3054/tx_refineries.py
analysis3054/uk_oil_products.py
analysis3054/utils.py
analysis3054/visualization.py
analysis3054/data/Spain_content_crude_oil_balance_refinery_output.csv
analysis3054/data/Spain_content_gas_consumption_by_market.csv
analysis3054/data/Spain_content_gas_consumption_by_pressure_bracket.csv
analysis3054/data/Spain_content_oil_products_all.csv
analysis3054/data/UK_content_et_3_12_month.csv
analysis3054/data/UK_content_et_3_13_month.csv
analysis3054/data/cftc_disagg_eligible_commodities.csv
analysis3054/data/cftc_disagg_filtered.csv
analysis3054/data/cftc_disagg_scatter_export.csv
analysis3054/data/cftc_disagg_seasonality_export.csv
analysis3054/data/dfo_generators_costs.csv
analysis3054/data/dfo_generators_inventory.csv
analysis3054-0.4.1.dist-info/licenses/LICENSE
analysis3054-0.4.1.dist-info/METADATA
analysis3054-0.4.1.dist-info/WHEEL
analysis3054-0.4.1.dist-info/top_level.txt
analysis3054-0.4.1.dist-info/RECORD
