Metadata-Version: 2.4
Name: analysis3054
Version: 0.4.1
Summary: Advanced time-series analytics and forecasting toolkit for commodity and power trading
Author-email: Hoff <you@example.com>
License: MIT
Requires-Python: >=3.10
License-File: LICENSE
Requires-Dist: pandas>=2.3.3
Requires-Dist: numpy<2.4.0,>=1.25.0
Requires-Dist: pycountry>=24.6.1
Requires-Dist: plotly>=6.5.0
Requires-Dist: statsmodels>=0.14.6
Requires-Dist: scipy>=1.16.3
Requires-Dist: holidays>=0.87
Requires-Dist: chronos-forecasting==2.2.2
Requires-Dist: autogluon.timeseries==1.5.0
Requires-Dist: requests>=2.32.5
Requires-Dist: httpx>=0.28.1
Requires-Dist: beautifulsoup4>=4.12.3
Requires-Dist: openpyxl>=3.1.2
Requires-Dist: pandas_datareader>=0.10.0
Requires-Dist: pdfplumber>=0.11.8
Requires-Dist: pypdf>=3.17.0
Requires-Dist: google-genai>=1.56.0
Requires-Dist: selenium>=4.27.0
Requires-Dist: stealthenium>=1.1.1
Requires-Dist: websocket-client>=1.8.0
Provides-Extra: stats
Requires-Dist: pmdarima>=2.1.1; extra == "stats"
Requires-Dist: arch>=8.0.0; extra == "stats"
Provides-Extra: ml
Requires-Dist: scikit-learn>=1.8.0; extra == "ml"
Requires-Dist: xgboost>=3.1.2; extra == "ml"
Requires-Dist: lightgbm>=4.6.0; extra == "ml"
Requires-Dist: catboost>=1.2.8; extra == "ml"
Provides-Extra: dl
Requires-Dist: tensorflow>=2.20.0; extra == "dl"
Provides-Extra: prophet
Requires-Dist: prophet>=1.2.1; extra == "prophet"
Requires-Dist: neuralprophet>=0.8.0; extra == "prophet"
Provides-Extra: physics
Requires-Dist: torch>=2.9.1; extra == "physics"
Requires-Dist: torchdiffeq>=0.2.5; extra == "physics"
Requires-Dist: PyWavelets>=1.9.0; extra == "physics"
Provides-Extra: tbats
Requires-Dist: tbats>=1.1.3; extra == "tbats"
Provides-Extra: autogluon
Requires-Dist: autogluon==1.5.0; extra == "autogluon"
Provides-Extra: plot
Requires-Dist: plotly>=6.5.0; extra == "plot"
Provides-Extra: playwright
Requires-Dist: playwright>=1.57.0; extra == "playwright"
Provides-Extra: seleniumbase
Requires-Dist: seleniumbase>=4.45.0; extra == "seleniumbase"
Provides-Extra: all
Requires-Dist: analysis3054[autogluon,dl,ml,physics,playwright,plot,prophet,seleniumbase,stats,tbats]; extra == "all"
Dynamic: license-file
